[
  {
    "angle": "Correctable Restatement",
    "eyebrow": "One message, one line to correct",
    "headline": "Your first message earns a one-line restatement you can correct.",
    "subheadline": "I restate the situation, goal, and uncertainty in one line; you confirm or correct it before advice begins.",
    "chatStarter": "Here is the messy version. Please tell me what you think I am actually saying.",
    "cta": "Check The One-Line Restatement",
    "proofLine": "10+ years teaching programming. Direct 1:1 support.",
    "priceLine": "$400–$520 a month",
    "whyItWorks": "A correctable mirror is a small, verifiable result from one rough message."
  },
  {
    "angle": "One-Question Reply",
    "eyebrow": "A reply, not a questionnaire",
    "headline": "A rough paragraph receives one clarifying question, not a questionnaire.",
    "subheadline": "The response asks only the question most capable of changing the next interpretation.",
    "chatStarter": "I can explain this in a paragraph, but I do not want to complete a questionnaire.",
    "cta": "Send The Rough Paragraph",
    "proofLine": "Direct 1:1 support. Start with a free 15-minute fit check.",
    "priceLine": "$400–$520 a month",
    "whyItWorks": "One clarifying question promises focus without pretending the first message contains enough context."
  },
  {
    "angle": "Action Label",
    "eyebrow": "Classify the work before expanding it",
    "headline": "One note earns a label: decide, diagnose, design, or delegate.",
    "subheadline": "Classify the work before choosing a tool, meeting, or specialist.",
    "chatStarter": "I do not know whether this is something to fix, decide, design, or hand off.",
    "cta": "Label The Work",
    "proofLine": "10+ years teaching programming. Direct 1:1 guidance.",
    "priceLine": "$400–$520 a month",
    "whyItWorks": "Four action labels give a rough message a useful operational category."
  },
  {
    "angle": "Consequence Sentence",
    "eyebrow": "Find the line that makes it matter",
    "headline": "The first reply highlights the sentence carrying the actual consequence.",
    "subheadline": "Find the line that explains why the issue matters, then use it to organize the technical details.",
    "chatStarter": "There are many details, but only one of them explains why this is a real problem.",
    "cta": "Highlight The Consequence",
    "proofLine": "10+ years teaching programming. Direct 1:1 support.",
    "priceLine": "$400–$520 a month",
    "whyItWorks": "Highlighting consequence creates priority without requiring a complete technical diagnosis."
  },
  {
    "angle": "Goal-Plan Contradiction",
    "eyebrow": "One message can reveal the pull",
    "headline": "One unpolished message can expose where your plan contradicts your goal.",
    "subheadline": "Compare the desired outcome with the current approach and name the first place they pull apart.",
    "chatStarter": "The plan sounds sensible, yet it may be working against the outcome we want.",
    "cta": "Find The Contradiction",
    "proofLine": "Direct 1:1 support. Start with a free 15-minute fit check.",
    "priceLine": "$400–$520 a month",
    "whyItWorks": "The contradiction produces immediate strategic value from minimal input."
  },
  {
    "angle": "Shared Definition",
    "eyebrow": "Find the word hiding two expectations",
    "headline": "Your opening note can identify the word both sides must define.",
    "subheadline": "Locate the term carrying two meanings so later agreement does not hide different expectations.",
    "chatStarter": "We keep agreeing on this word, but I suspect we mean different things by it.",
    "cta": "Name The Shared Definition",
    "proofLine": "10+ years teaching programming. Direct 1:1 guidance.",
    "priceLine": "$400–$520 a month",
    "whyItWorks": "A shared definition prevents false agreement and gives the exchange a precise result."
  },
  {
    "angle": "Fact Or Choice",
    "eyebrow": "Know whether to investigate or decide",
    "headline": "The reply distinguishes a missing fact from a missing choice.",
    "subheadline": "Clarify whether progress needs new information or the courage to choose with what is already known.",
    "chatStarter": "I cannot tell whether we lack information or are postponing a choice.",
    "cta": "Separate Fact From Choice",
    "proofLine": "10+ years teaching programming. Direct 1:1 support.",
    "priceLine": "$400–$520 a month",
    "whyItWorks": "The distinction tells the client whether to investigate or decide."
  },
  {
    "angle": "Calibrated First Reply",
    "eyebrow": "Confidence with a visible level",
    "headline": "One rough message receives a confidence level, not borrowed certainty.",
    "subheadline": "The response states what seems likely, what remains uncertain, and why.",
    "chatStarter": "Give me your confidence level, not a definitive answer the evidence cannot support.",
    "cta": "Ask For Calibrated Confidence",
    "proofLine": "Direct 1:1 support. Start with a free 15-minute fit check.",
    "priceLine": "$400–$520 a month",
    "whyItWorks": "A confidence level makes uncertainty useful without overpromising an answer."
  },
  {
    "angle": "Known-Assumed Split",
    "eyebrow": "Two columns from one note",
    "headline": "A single note can produce a two-column known-versus-assumed split.",
    "subheadline": "Separate what the message establishes from what the current explanation assumes.",
    "chatStarter": "This message mixes what happened with my theory about why.",
    "cta": "Split Known From Assumed",
    "proofLine": "10+ years teaching programming. Direct 1:1 guidance.",
    "priceLine": "$400–$520 a month",
    "whyItWorks": "The two-column split turns a mixed message into inspectable reasoning."
  },
  {
    "angle": "Testable Claim",
    "eyebrow": "One claim inside the larger concern",
    "headline": "The first reply names the smallest claim worth testing.",
    "subheadline": "Reduce the larger concern to one statement that a small experiment could confirm or reject.",
    "chatStarter": "The concern is broad; help me find one claim we could actually test.",
    "cta": "Name The Testable Claim",
    "proofLine": "10+ years teaching programming. Direct 1:1 support.",
    "priceLine": "$400–$520 a month",
    "whyItWorks": "One testable claim is a believable improvement over an unresolved concern."
  },
  {
    "angle": "User-Dependent Problem",
    "eyebrow": "Check whether the person changes the problem",
    "headline": "One message can reveal whether the problem changes with the user.",
    "subheadline": "Check whether the issue belongs to one person, role, account, device, or situation before generalizing it.",
    "chatStarter": "The issue appears for some people and not others, and that difference may matter.",
    "cta": "Check Who Changes It",
    "proofLine": "Direct 1:1 support. Start with a free 15-minute fit check.",
    "priceLine": "$400–$520 a month",
    "whyItWorks": "User dependence stops premature generalization and sharpens the next question."
  },
  {
    "angle": "Boundary Case",
    "eyebrow": "Find where generic advice stops",
    "headline": "Your rough note can uncover the boundary case that breaks generic advice.",
    "subheadline": "Find the case where the recommendation would stop working before treating it as universal.",
    "chatStarter": "This advice sounds right generally, but I want to know where it would fail.",
    "cta": "Find The Boundary Case",
    "proofLine": "10+ years teaching programming. Direct 1:1 guidance.",
    "priceLine": "$400–$520 a month",
    "whyItWorks": "A boundary case gives generic advice a specific, honest limit."
  },
  {
    "angle": "Developer Sentence",
    "eyebrow": "One answerable line for implementation",
    "headline": "The reply isolates the sentence your developer actually needs answered.",
    "subheadline": "Extract the choice, constraint, or acceptance condition the implementer cannot safely infer.",
    "chatStarter": "My developer is waiting, and I need to identify the exact sentence requiring an answer.",
    "cta": "Find The Developer Question",
    "proofLine": "10+ years teaching programming. Direct 1:1 support.",
    "priceLine": "$400–$520 a month",
    "whyItWorks": "The implementer sentence converts a message into immediate coordination value."
  },
  {
    "angle": "Precise Show-Me Request",
    "eyebrow": "Know exactly what to show next",
    "headline": "One message can earn a precise ‘show me this’ request.",
    "subheadline": "Identify the exact screen, result, step, or artifact that would let the conversation become more precise.",
    "chatStarter": "Tell me exactly what you need me to show next.",
    "cta": "Learn What To Show",
    "proofLine": "Direct 1:1 support. Start with a free 15-minute fit check.",
    "priceLine": "$400–$520 a month",
    "whyItWorks": "A precise show-me request gives the client a tiny, obvious next action."
  },
  {
    "angle": "Screenshot Purpose",
    "eyebrow": "The next image has one job",
    "headline": "Your first note gives the next screenshot a specific purpose.",
    "subheadline": "Know what the screenshot should prove or disprove before adding another image to the thread.",
    "chatStarter": "I can send screenshots, but I want the next one to answer a specific question.",
    "cta": "Aim The Next Screenshot",
    "proofLine": "10+ years teaching programming. Direct 1:1 guidance.",
    "priceLine": "$400–$520 a month",
    "whyItWorks": "Purpose turns another screenshot into evidence rather than context volume."
  },
  {
    "angle": "Diagnostic Sequence",
    "eyebrow": "Order the details before adding more",
    "headline": "A rough paragraph narrows ten details to one diagnostic sequence.",
    "subheadline": "Order the details by what happened first, what changed, and where the outcome diverged.",
    "chatStarter": "Ten details may matter, but I need the sequence that makes them diagnostic.",
    "cta": "Build The Diagnostic Sequence",
    "proofLine": "10+ years teaching programming. Direct 1:1 support.",
    "priceLine": "$400–$520 a month",
    "whyItWorks": "Sequence is a compact, useful transformation for messy diagnostic detail."
  },
  {
    "angle": "Counterexample Reply",
    "eyebrow": "One exception to test the plan",
    "headline": "The first response offers a counterexample capable of challenging your plan.",
    "subheadline": "Use one plausible exception to test whether the plan is robust or merely comfortable.",
    "chatStarter": "The plan feels convincing; challenge it with one case it may not handle.",
    "cta": "Challenge It With One Case",
    "proofLine": "10+ years teaching programming. Direct 1:1 guidance.",
    "priceLine": "$400–$520 a month",
    "whyItWorks": "One counterexample adds rigor without requiring a full review."
  },
  {
    "angle": "Definition Divergence",
    "eyebrow": "Find where agreement splits",
    "headline": "One note can locate where two reasonable definitions split.",
    "subheadline": "Find the point where two people use the same term for different requirements.",
    "chatStarter": "We use the same term and still expect different outcomes.",
    "cta": "Locate The Definition Split",
    "proofLine": "10+ years teaching programming. Direct 1:1 support.",
    "priceLine": "$400–$520 a month",
    "whyItWorks": "Definition divergence explains disagreement without assigning fault."
  },
  {
    "angle": "Second-Case Check",
    "eyebrow": "See whether the explanation travels",
    "headline": "The reply tests whether your problem survives beyond one example.",
    "subheadline": "Check whether the explanation accounts for a second case or only retells the first.",
    "chatStarter": "This explanation fits one example; I do not know whether it explains the pattern.",
    "cta": "Test Beyond One Example",
    "proofLine": "Direct 1:1 support. Start with a free 15-minute fit check.",
    "priceLine": "$400–$520 a month",
    "whyItWorks": "A second-case check distinguishes explanation from storytelling."
  },
  {
    "angle": "Inherited Constraint",
    "eyebrow": "Check whether the limit is still real",
    "headline": "Your opening message can separate a real constraint from an inherited one.",
    "subheadline": "Distinguish a current limit from a rule carried forward from an older tool, team, or decision.",
    "chatStarter": "This constraint may be real, or we may simply have inherited it from an older setup.",
    "cta": "Check The Inherited Constraint",
    "proofLine": "10+ years teaching programming. Direct 1:1 guidance.",
    "priceLine": "$400–$520 a month",
    "whyItWorks": "Inherited constraints are common, specific, and easy to inspect after one message."
  },
  {
    "angle": "Blocked Or Uncomfortable",
    "eyebrow": "Name the actual work state",
    "headline": "One rough note distinguishes blocked work from uncomfortable work.",
    "subheadline": "Identify whether work cannot proceed or simply requires a difficult, uncertain, or unfamiliar choice.",
    "chatStarter": "The work feels blocked, but it may actually be a difficult decision we are avoiding.",
    "cta": "Separate Blocked From Uncomfortable",
    "proofLine": "10+ years teaching programming. Direct 1:1 support.",
    "priceLine": "$400–$520 a month",
    "whyItWorks": "The distinction replaces emotional pressure with a more accurate work state."
  },
  {
    "angle": "Costliest Ambiguity",
    "eyebrow": "Find the vague part likely to create rework",
    "headline": "The first reply points to the ambiguity most capable of wasting effort.",
    "subheadline": "Find the undefined outcome, owner, boundary, or condition most likely to create rework.",
    "chatStarter": "The brief contains several vague parts, and I need to find the one most likely to cause rework.",
    "cta": "Find The Costliest Ambiguity",
    "proofLine": "Direct 1:1 support. Start with a free 15-minute fit check.",
    "priceLine": "$400–$520 a month",
    "whyItWorks": "One costly ambiguity is a bounded outcome with immediate practical value."
  },
  {
    "angle": "Answerable Subquestion",
    "eyebrow": "Find the first binary branch",
    "headline": "One paragraph can yield a yes-or-no question worth answering first.",
    "subheadline": "Reduce the broad issue to one binary distinction that determines which branch deserves attention.",
    "chatStarter": "The question is too broad; help me reduce it to the first yes-or-no distinction.",
    "cta": "Ask The First Binary Question",
    "proofLine": "10+ years teaching programming. Direct 1:1 guidance.",
    "priceLine": "$400–$520 a month",
    "whyItWorks": "A binary subquestion creates a clear first branch without oversimplifying the whole problem."
  },
  {
    "angle": "Useful Verb",
    "eyebrow": "Fix may be the wrong action",
    "headline": "The reply replaces ‘fix this’ with the action your situation actually needs.",
    "subheadline": "Clarify whether the next move is to compare, inspect, test, explain, decide, or defer.",
    "chatStarter": "I keep saying fix this, but the situation may need a different action entirely.",
    "cta": "Find The Useful Verb",
    "proofLine": "10+ years teaching programming. Direct 1:1 support.",
    "priceLine": "$400–$520 a month",
    "whyItWorks": "A better verb makes the next action precise before advice expands."
  },
  {
    "angle": "Preference Or Dependency",
    "eyebrow": "Find what is really forcing the choice",
    "headline": "Your first message can expose a dependency disguised as a preference.",
    "subheadline": "Check whether a stated preference is actually protecting a tool, dependency, skill gap, or past commitment.",
    "chatStarter": "We call this a preference, but something seems to be forcing it.",
    "cta": "Expose The Hidden Dependency",
    "proofLine": "Direct 1:1 support. Start with a free 15-minute fit check.",
    "priceLine": "$400–$520 a month",
    "whyItWorks": "Reframing preference as dependency reveals what actually limits the choice."
  },
  {
    "angle": "Conversation Stop",
    "eyebrow": "Give the next exchange an ending",
    "headline": "One rough note gives the next conversation a stopping condition.",
    "subheadline": "Define what answer, evidence, or boundary would let the next exchange close usefully.",
    "chatStarter": "I want this next conversation to have a useful stopping point.",
    "cta": "Set The Conversation Stop",
    "proofLine": "10+ years teaching programming. Direct 1:1 guidance.",
    "priceLine": "$400–$520 a month",
    "whyItWorks": "A stopping condition keeps the next exchange purposeful and finite."
  },
  {
    "angle": "Example Value Check",
    "eyebrow": "Know whether more context will help",
    "headline": "The reply can decide whether one concrete example would change the answer.",
    "subheadline": "Decide whether one real case would resolve the uncertainty or merely add another anecdote.",
    "chatStarter": "I can provide an example, but I want to know whether it would actually change the answer.",
    "cta": "Check The Example Value",
    "proofLine": "10+ years teaching programming. Direct 1:1 support.",
    "priceLine": "$400–$520 a month",
    "whyItWorks": "It tests whether more context would create evidence or only volume."
  },
  {
    "angle": "Next Check Or Stop",
    "eyebrow": "Two useful outcomes from one message",
    "headline": "A single message earns either a next check or a reason to stop.",
    "subheadline": "The response either identifies a useful action or explains why continuing now would add noise.",
    "chatStarter": "Tell me whether there is a useful next check or whether we should stop here.",
    "cta": "Find Check Or Stop",
    "proofLine": "Direct 1:1 support. Start with a free 15-minute fit check.",
    "priceLine": "$400–$520 a month",
    "whyItWorks": "Two honest outcomes keep the one-message promise small and trustworthy."
  },
  {
    "angle": "Alternative Framing",
    "eyebrow": "See the message through two useful lenses",
    "headline": "One rough message can receive two framings—and reveal which one fits.",
    "subheadline": "Read the same situation as a technical failure and as a decision problem, then choose the more useful lens.",
    "chatStarter": "I can describe this as a technical failure or a decision problem, and I do not know which framing helps.",
    "cta": "Compare The Two Framings",
    "proofLine": "10+ years teaching programming. Direct 1:1 guidance.",
    "priceLine": "$400–$520 a month",
    "whyItWorks": "Two framings reveal which kind of conversation can produce progress."
  },
  {
    "angle": "Question Scope Test",
    "eyebrow": "Broad, early, or ready",
    "headline": "The reply identifies whether your question is too broad, too early, or ready.",
    "subheadline": "Classify the question before answering it, so the next exchange matches its actual readiness.",
    "chatStarter": "I need to know whether this question is ready, premature, or simply too broad.",
    "cta": "Test The Question Scope",
    "proofLine": "10+ years teaching programming. Direct 1:1 support.",
    "priceLine": "$400–$520 a month",
    "whyItWorks": "Readiness classification gives one message a concrete, non-inflated result."
  }
]
